<?xml version="1.0" encoding="UTF-8"?>
<metadata xml:lang="zh"><Esri><CreaDate>20191229</CreaDate><CreaTime>23185300</CreaTime><ArcGISFormat>1.0</ArcGISFormat><SyncOnce>TRUE</SyncOnce><DataProperties><lineage><Process ToolSource="c:\program files (x86)\arcgis\desktop10.7\ArcToolbox\Toolboxes\Spatial Analyst Tools.tbx\RasterCalculator" Date="20191229" Time="231853">RasterCalculator ("TEM_Interpret_Ex.tif" + "Com_TEM_PRE_Ex.tif"/2)*1.0/("TEM_Interpret_Ex.tif"+"PRE_Interpret_Ex.tif"+"Com_TEM_PRE_Ex.tif") G:\Result_Summary_1223\Figs\Test_Fig6\Proportion_TEM_Interpretation.tif</Process></lineage></DataProperties></Esri></metadata>
